rikai/experimental/torchhub/__init__.py
rikai/experimental/torchhub/torchhub_registry.py
rikai_torchhub-0.1.0.dist-info/METADATA
rikai_torchhub-0.1.0.dist-info/WHEEL
rikai_torchhub-0.1.0.dist-info/top_level.txt
rikai_torchhub-0.1.0.dist-info/RECORD
